<?xml version="1.0" encoding="UTF-8"?><record_update table="sys_transform_entry">
    <sys_transform_entry action="DELETE">
        <choice_action>create</choice_action>
        <coalesce>false</coalesce>
        <coalesce_case_sensitive>false</coalesce_case_sensitive>
        <coalesce_empty_fields>false</coalesce_empty_fields>
        <date_format>yyyy-MM-dd HH:mm:ss</date_format>
        <map display_value="Sprint 2 stories">40c9222783ad5210b8bec7c6feaad3af</map>
        <reference_value_field/>
        <source_field>u_epic</source_field>
        <source_script><![CDATA[answer = (function transformEntry(source) {

	// Add your code here
	return ""; // return the value to be put into the target field

})(source);]]></source_script>
        <source_table>x_1553691_lva_sprint_2_stories</source_table>
        <sys_class_name>sys_transform_entry</sys_class_name>
        <sys_created_by>shari.lemonnier</sys_created_by>
        <sys_created_on>2024-11-04 23:41:18</sys_created_on>
        <sys_id>ef8b66a783ad5210b8bec7c6feaad354</sys_id>
        <sys_mod_count>0</sys_mod_count>
        <sys_name>u_epic</sys_name>
        <sys_package display_value="Loaner Vehicle Request and Inventory" source="x_1553691_lva">8b6ad87f8351d610b8bec7c6feaad38c</sys_package>
        <sys_policy/>
        <sys_scope display_value="Loaner Vehicle Request and Inventory">8b6ad87f8351d610b8bec7c6feaad38c</sys_scope>
        <sys_update_name>sys_transform_entry_ef8b66a783ad5210b8bec7c6feaad354</sys_update_name>
        <sys_updated_by>shari.lemonnier</sys_updated_by>
        <sys_updated_on>2024-11-04 23:41:18</sys_updated_on>
        <target_field>epic</target_field>
        <target_table>rm_story</target_table>
        <use_source_script>false</use_source_script>
    </sys_transform_entry>
    <sys_update_version action="INSERT_OR_UPDATE">
        <action>DELETE</action>
        <application display_value="Loaner Vehicle Request and Inventory">8b6ad87f8351d610b8bec7c6feaad38c</application>
        <file_path/>
        <instance_id>02da4e7ddbfdb594ae4c9027c59619d5</instance_id>
        <instance_name>dev182749</instance_name>
        <name>sys_transform_entry_ef8b66a783ad5210b8bec7c6feaad354</name>
        <payload>&lt;?xml version="1.0" encoding="UTF-8"?&gt;&lt;record_update table="sys_transform_entry"&gt;&lt;sys_transform_entry action="INSERT_OR_UPDATE"&gt;&lt;choice_action&gt;create&lt;/choice_action&gt;&lt;coalesce&gt;false&lt;/coalesce&gt;&lt;coalesce_case_sensitive&gt;false&lt;/coalesce_case_sensitive&gt;&lt;coalesce_empty_fields&gt;false&lt;/coalesce_empty_fields&gt;&lt;date_format&gt;yyyy-MM-dd HH:mm:ss&lt;/date_format&gt;&lt;map display_value="Sprint 2 stories"&gt;40c9222783ad5210b8bec7c6feaad3af&lt;/map&gt;&lt;reference_value_field/&gt;&lt;source_field&gt;u_epic&lt;/source_field&gt;&lt;source_script&gt;&lt;![CDATA[answer = (function transformEntry(source) {

	// Add your code here
	return ""; // return the value to be put into the target field

})(source);]]&gt;&lt;/source_script&gt;&lt;source_table&gt;x_1553691_lva_sprint_2_stories&lt;/source_table&gt;&lt;sys_class_name&gt;sys_transform_entry&lt;/sys_class_name&gt;&lt;sys_created_by&gt;shari.lemonnier&lt;/sys_created_by&gt;&lt;sys_created_on&gt;2024-11-04 23:41:18&lt;/sys_created_on&gt;&lt;sys_id&gt;ef8b66a783ad5210b8bec7c6feaad354&lt;/sys_id&gt;&lt;sys_mod_count&gt;0&lt;/sys_mod_count&gt;&lt;sys_name&gt;u_epic&lt;/sys_name&gt;&lt;sys_package display_value="Loaner Vehicle Request and Inventory" source="x_1553691_lva"&gt;8b6ad87f8351d610b8bec7c6feaad38c&lt;/sys_package&gt;&lt;sys_policy/&gt;&lt;sys_scope display_value="Loaner Vehicle Request and Inventory"&gt;8b6ad87f8351d610b8bec7c6feaad38c&lt;/sys_scope&gt;&lt;sys_update_name&gt;sys_transform_entry_ef8b66a783ad5210b8bec7c6feaad354&lt;/sys_update_name&gt;&lt;sys_updated_by&gt;shari.lemonnier&lt;/sys_updated_by&gt;&lt;sys_updated_on&gt;2024-11-04 23:41:18&lt;/sys_updated_on&gt;&lt;target_field&gt;epic&lt;/target_field&gt;&lt;target_table&gt;rm_story&lt;/target_table&gt;&lt;use_source_script&gt;false&lt;/use_source_script&gt;&lt;/sys_transform_entry&gt;&lt;/record_update&gt;</payload>
        <payload_hash>-1172996201</payload_hash>
        <record_name>u_epic</record_name>
        <reverted_from/>
        <source>51cc1ec883ed1a10b8bec7c6feaad3aa</source>
        <source_table>sys_update_set</source_table>
        <state>previous</state>
        <sys_created_by>shari.lemonnier</sys_created_by>
        <sys_created_on>2024-11-04 23:41:18</sys_created_on>
        <sys_id>2f8b66a783ad5210b8bec7c6feaad356</sys_id>
        <sys_mod_count>0</sys_mod_count>
        <sys_recorded_at>192f98de1c80000001</sys_recorded_at>
        <sys_updated_by>shari.lemonnier</sys_updated_by>
        <sys_updated_on>2024-11-04 23:41:18</sys_updated_on>
        <type>Field Map</type>
        <update_guid>238b66a782ad5210527301979449c256</update_guid>
        <update_guid_history>238b66a782ad5210527301979449c256:-1172996201</update_guid_history>
    </sys_update_version>
    <sys_metadata_delete action="INSERT_OR_UPDATE">
        <sys_audit_delete/>
        <sys_class_name>sys_metadata_delete</sys_class_name>
        <sys_created_by>shari.lemonnier</sys_created_by>
        <sys_created_on>2025-01-10 20:54:49</sys_created_on>
        <sys_db_object display_value="" name="sys_transform_entry">sys_transform_entry</sys_db_object>
        <sys_id>ac64ccb1cd59431c808b9c3814d90210</sys_id>
        <sys_metadata>ef8b66a783ad5210b8bec7c6feaad354</sys_metadata>
        <sys_mod_count>0</sys_mod_count>
        <sys_name>u_epic</sys_name>
        <sys_package display_value="Loaner Vehicle Request and Inventory" source="x_1553691_lva">8b6ad87f8351d610b8bec7c6feaad38c</sys_package>
        <sys_parent/>
        <sys_policy/>
        <sys_scope display_value="Loaner Vehicle Request and Inventory">8b6ad87f8351d610b8bec7c6feaad38c</sys_scope>
        <sys_scope_delete display_value="">3ac61e579acd4ef0a8eb4e291b6d2921</sys_scope_delete>
        <sys_update_name>sys_transform_entry_ef8b66a783ad5210b8bec7c6feaad354</sys_update_name>
        <sys_update_version display_value="sys_transform_entry_ef8b66a783ad5210b8bec7c6feaad354">2f8b66a783ad5210b8bec7c6feaad356</sys_update_version>
        <sys_updated_by>shari.lemonnier</sys_updated_by>
        <sys_updated_on>2025-01-10 20:54:49</sys_updated_on>
    </sys_metadata_delete>
</record_update>
